{
  "id": "2080",
  "nom": "Pointe de Celse Niere, par le Vallon de Clapouse",
  "orientation": "E",
  "denivele": "1900",
  "dif_ski": "3.3",
  "expo": "2",
  "difficulte": "PD-",
  "gpx": null,
  "massif": {
    "id": "7",
    "nom": "Ecrins"
  },
  "depart": {
    "id": "339",
    "nom": "Ailefroide",
    "altitude": "1522",
    "acces": "Briançon ou Gap &gt; l'Argentière la Bessée &gt; Vallouise &gt; Pelvoux &gt;  Ailefroide &gt; Parking 1522\r\nEn hiver la route est fermée par une barrière à la sortie de Pelvoux les Claux (1270m)",
    "latlon": [
      "44.8822",
      "6.4431"
    ]
  },
  "sommets": {
    "1": {
      "id": "1627",
      "nom": "Pointe de Celse Niere",
      "altitude": "3429",
      "latlon": [
        "44.8627",
        "6.3949"
      ]
    }
  },
  "refuges": [],
  "variantes": [],
  "materiel": "Crampons, piolet",
  "presentation": "",
  "itineraire": "Remonter le vallon du Sélé jusqu'à la passerelle (1572m) permettant de passer en rive droite du torrent de Celse Nière. Suivre ensuite le tracé du sentier d'été pour atteindre le vallon de Clapouse (par bon enneigement, on peut aussi monter (et descendre) par la combe/ravin au NE de la Bosse de Clapouse).\r\nRemonter le vallon jusque sous le collet du Rascrouset, puis tourner à droite en direction du petit glacier de Clapouse. Vers 3200m, rejoindre à gauche la crête séparant le glacier de Clapouse du glacier du Rascrouset et la suivre jusqu'à ce qu'elle vienne buter sous les rochers sommitaux (~3390m). L'accès au point culminant semble assez compliqué, surtout avec les chaussures de ski. \r\n\r\n\r\n  ",
  "remarques": "",
  "biblio": "",
  "auteur": {
    "id": "1818",
    "pseudo": "valb26"
  },
  "photos": {
    "1": {
      "id": "1433",
      "com": "Partie superieure du Vallon de Clapouse",
      "url": "/topos/photos/1433.jpg",
      "auteur": {
        "id": "1321",
        "pseudo": "PatdeGap"
      }
    },
    "2": {
      "id": "5257",
      "com": "Bosse de Clapouse, passage compliqué pour débuter et finir la rando.",
      "url": "/topos/photos/5257.jpg",
      "auteur": {
        "id": "8319",
        "pseudo": "L-Ric"
      }
    }
  }
}