{
  "id": "8841",
  "nom": "Crête de la Rantzei, Couloir SW",
  "orientation": "SW",
  "denivele": "1450",
  "dif_ski": "3.2",
  "expo": "2",
  "difficulte": "F",
  "gpx": null,
  "massif": {
    "id": "18",
    "nom": "Vanoise"
  },
  "depart": {
    "id": "57",
    "nom": "Lanslevillard, Pré Clos",
    "altitude": "1690",
    "acces": "Modane &gt; Lanslevillard-&gt;Pré Clos (après l'épingle, avant le col de la Madeleine).",
    "latlon": [
      "45.2997",
      "6.9359"
    ]
  },
  "sommets": {
    "1": {
      "id": "6608",
      "nom": "Crête de la Rantzei",
      "altitude": "3135",
      "latlon": [
        "45.3272",
        "6.93652"
      ]
    }
  },
  "refuges": {
    "1": {
      "id": "68",
      "nom": "Refuge de Vallonbrun",
      "altitude": "2270",
      "latlon": [
        "45.3103",
        "6.9372"
      ]
    }
  },
  "variantes": [],
  "materiel": "Classique",
  "presentation": "Cette face/couloir permet une belle incursion dans le plan des Glières sans aller trop dans le raide; A faire l'après-midi lors d'une première montée au refuge de Vallonbrun (ou pour repérer les couloirs du secteur). ",
  "itineraire": "Depuis Pré Clos, suivre le sentier de Côte plane menant au refuge de Vallonbrun. Au replat de la Fesse d'en bas (vers 2200m), continuez tout droit en visant le Chélou (on laisse alors main droite le sentier pour le refuge) puis le Plan des Glières (vers 2500m). De là suivre le vallon évident plein nord en direction des crêtes de Vallonbrun. On passe alors sous la Crête de la Rantzei. Sous les crêtes de Vallonbrun, vers 2800m, remonter la combe orientée SW qui mène à un collu entre la crête de la Rantzeil et la Pointe de Vallonbrun, final un peu raide (37/38°). ",
  "remarques": "Il doit être possible de poursuivre au-dessus du col pour aller aux Crêtes de Vallonbrun, la cotation augmente alors (dans le 4.x ??). ",
  "biblio": "",
  "auteur": {
    "id": "10548",
    "pseudo": "Em42"
  },
  "photos": {
    "1": {
      "id": "7473",
      "com": "Itinéraire vu depuis la Pointe de la Frèche",
      "url": "/topos/photos/7473.jpg",
      "auteur": {
        "id": "10548",
        "pseudo": "Em42"
      }
    }
  }
}