{
  "id": "952",
  "nom": "Capu Biancu, Monte Biancu",
  "orientation": "S",
  "denivele": "1800",
  "dif_ski": "3.1",
  "expo": "1",
  "difficulte": "F",
  "gpx": null,
  "massif": {
    "id": "33",
    "nom": "Corse"
  },
  "depart": {
    "id": "490",
    "nom": "Corscia",
    "altitude": "880",
    "acces": "De Francardo prendre la vallée du Niolo D84  direction Calacuccia. Première route à droite D 718 après les gorges (scala) direction Corscia. Se garer à proximité de l'église de Corscia",
    "latlon": [
      "42.3551",
      "9.04022"
    ]
  },
  "sommets": {
    "1": {
      "id": "762",
      "nom": "Capu Biancu",
      "altitude": "2562",
      "latlon": [
        "42.4027",
        "8.98855"
      ]
    }
  },
  "refuges": [],
  "variantes": [],
  "materiel": "",
  "presentation": "",
  "itineraire": "De l'église de Corsica, descendre sur 100m vers le hameau de Cavallaracce pour prendre le sentier de randonnée Corte - Ile Rousse balisé en orange. Passer les portes (2 ou3) des clotures EN PENSANT A BIEN LES REFERMER car enclos à vaches (possibilité de contourner par la gauche). Au fond de l'enclos suivre un chemin à flan jusqu au ruisseau 1000m. Ne pas traverser le gros ruisseau monter en face au mieux jusqu'à la crête puis basculer vers les bergeries de Caracuto en suivant le GR que l'on vient de rattraper. Des bergeries, suivre le fond du vallon puis rejoindre le sommet . ",
  "remarques": "A faire avec de l'enneigement pour le bas (1100 m)= 45 min de portage",
  "biblio": "",
  "auteur": {
    "id": "1183",
    "pseudo": "RNO"
  },
  "photos": {
    "1": {
      "id": "102",
      "com": "sommet du Capu Biancu",
      "url": "/topos/photos/102.jpg",
      "auteur": {
        "id": "1183",
        "pseudo": "RNO"
      }
    }
  }
}