{
  "id": "2004",
  "nom": "Germas, Combe Nord",
  "orientation": "N",
  "denivele": "1075",
  "dif_ski": "3.1",
  "expo": "2",
  "difficulte": "F",
  "gpx": null,
  "massif": {
    "id": "5",
    "nom": "Ubaye - Parpaillon - Alpes Cozie S"
  },
  "depart": {
    "id": "632",
    "nom": "Maison-Méane",
    "altitude": "1776",
    "acces": "Barcelonnette, direction col de Larche.\r\nMaison-Méane est le paté de maisons sur la route du col de Larche 2km environ après le village de Larche",
    "latlon": [
      "44.4408",
      "6.86435"
    ]
  },
  "sommets": {
    "1": {
      "id": "1580",
      "nom": "Germas",
      "altitude": "2749",
      "latlon": [
        "44.42",
        "6.83083"
      ]
    }
  },
  "refuges": [],
  "variantes": [
    {
      "id": 1,
      "nom": "Couloir NE",
      "denivele": "1200",
      "ski": "4.3",
      "orientation": "NE",
      "description": "Pente large au départ, puis ça s'incline jusqu'à 45° et se resserre (voir photo)"
    },
    {
      "id": 2,
      "nom": "Couloir E",
      "denivele": "1200",
      "ski": "4.2",
      "orientation": "E",
      "description": "Passe entre deux failles rocheuses, assez étroit (4 m environ). Bien visible depuis l'itinéraire SE, rectiligne."
    },
    {
      "id": 3,
      "nom": "Voie SE",
      "denivele": "1200",
      "ski": "3.1",
      "orientation": "SE",
      "description": "Montée en contournant par le SE. Un passage plus raide (40°) pour accéder à la combe supérieure."
    }
  ],
  "materiel": "Crampons peuvent être nécessaire pour la crête sur l'épaule gauche. \r\nP.S.A.",
  "presentation": "",
  "itineraire": "Du parking, descendre au Sud en passant près du cimetière vers le pont qui vous permettra de traverser l'Ubayette. Remonter alors la route du Lauzanier sur 50m pour trouver sur votre droite un sentier qui vous permettra de rejoindre le vallon de Courruit après une traversée oblique assez raide dans la forêt. Suivre le vallon jusqu'à la cabane de Courruit, puis se diriger vers la droite pour rejoindre le vallon Bernard. Vers 2400, on découvre à gauche la petite combe Nord que l'on remonte, soit directement, soit en rejoignant la crête de gauche, pour atteindre le sommet par des pentes plus douces.\r\n\r\n\r\n\r\n\r\n\r\n",
  "remarques": "Départ aussi possible du camping, pt 1677 (accès déneigé)",
  "biblio": "",
  "auteur": {
    "id": "755",
    "pseudo": "skiroad"
  },
  "photos": {
    "1": {
      "id": "1007",
      "com": "itinéraire Combe Nord",
      "url": "/topos/photos/1007.jpg",
      "auteur": {
        "id": "755",
        "pseudo": "skiroad"
      }
    },
    "2": {
      "id": "5924",
      "com": "Bleu : itinéraire SE (montée &quot;classique&quot;)\r\nOrange : couloir E\r\nRouge couloir NE",
      "url": "/topos/photos/5924.jpg",
      "auteur": {
        "id": "6715",
        "pseudo": "pol"
      }
    }
  }
}