{
  "id": "928",
  "nom": "Col des Portes, par la Casse des Clausins (versant Sud)",
  "orientation": "S",
  "denivele": "1090",
  "dif_ski": "3.1",
  "expo": "1",
  "difficulte": "F",
  "gpx": null,
  "massif": {
    "id": "6",
    "nom": "Queyras - Alpes Cozie N"
  },
  "depart": {
    "id": "476",
    "nom": "Souliers",
    "altitude": "1830",
    "acces": "Guillestre -&gt; Château-Queyras &gt; suivre au nord la route qui mène à Souliers. On se gare sur un parking aménagé au niveau de la petite chapelle.",
    "latlon": [
      "44.776",
      "6.76762"
    ]
  },
  "sommets": {
    "1": {
      "id": "742",
      "nom": "Col des Portes",
      "altitude": "2916",
      "latlon": [
        "44.8193",
        "6.7823"
      ]
    }
  },
  "refuges": {
    "1": {
      "id": "452",
      "nom": "le grand Rochebrune",
      "altitude": "1840",
      "latlon": [
        "44.7789",
        "6.76826"
      ]
    }
  },
  "variantes": [],
  "materiel": "",
  "presentation": "",
  "itineraire": "Remonter le vallon de Souliers vers le Nord, d'abord en rive gauche (piste), puis en rive droite. Dépasser la bergerie (2075m), et vers 2150m monter à droite le long du torrent de Souliers pour rejoindre la Casse des Clausins.\r\nSe diriger alors N-NE en direction du col que l'on atteint par une pente soutenue (sup à 30°)\r\n\r\n\r\n",
  "remarques": "",
  "biblio": "",
  "auteur": {
    "id": "1001",
    "pseudo": "Jan"
  },
  "photos": {
    "1": {
      "id": "1533",
      "com": "Col des Portes vue de la casse des Clausins",
      "url": "/topos/photos/1533.jpg",
      "auteur": {
        "id": "3219",
        "pseudo": "zigual"
      }
    }
  }
}