{
  "id": "1237",
  "nom": "Seehorn, normale",
  "orientation": "W",
  "denivele": "1260",
  "dif_ski": "2.1",
  "expo": "1",
  "difficulte": "F",
  "gpx": null,
  "massif": {
    "id": "27",
    "nom": "Valais E - Alpes Pennines E"
  },
  "depart": {
    "id": "644",
    "nom": "Gabi",
    "altitude": "1200",
    "acces": "Martigny -&gt; Sion -&gt; Brig -&gt; col du Simplon -&gt; Gabi (parking devant l'hôtel)",
    "latlon": [
      "46.1842",
      "8.07255"
    ]
  },
  "sommets": {
    "1": {
      "id": "989",
      "nom": "Seehorn",
      "altitude": "2438",
      "latlon": [
        "46.1834",
        "8.1172"
      ]
    }
  },
  "refuges": {
    "1": {
      "id": "84",
      "nom": "Hospice du Simplon",
      "altitude": "2010",
      "latlon": [
        "46.2466",
        "8.02909"
      ]
    }
  },
  "variantes": [],
  "materiel": "",
  "presentation": "",
  "itineraire": "Au fond du parking, prendre le large chemin plein sud le long de la rive gauche du torrent sur 600m environ. Traverser le torrent sur le pont en direction Est et continuer au mieux dans les mélèzes en suivant la ligne des chalets d'alpage. On sort de la forêt vers 2000m. Aller chercher l'arête sud du Seehorn et la remonter plein nord jusqu'au sommet. Descente en profitant en général d'une bonne poudreuse dans les mélèzes.",
  "remarques": "Belle course à faire de préférence en poudreuse.\r\nAu retour, allez au bar de l'Hôtel Gabi mais ne faites pas comme Napoléon, au lieu du lait, une bonne pression est recommandée pour 2€.",
  "biblio": "",
  "auteur": {
    "id": "1107",
    "pseudo": "Robzz"
  },
  "photos": {
    "1": {
      "id": "330",
      "com": "Parking du départ",
      "url": "/topos/photos/330.jpg",
      "auteur": {
        "id": "1107",
        "pseudo": "Robzz"
      }
    },
    "2": {
      "id": "331",
      "com": "Itinéraire",
      "url": "/topos/photos/331.jpg",
      "auteur": {
        "id": "1107",
        "pseudo": "Robzz"
      }
    }
  }
}