{
  "id": "8544",
  "nom": "Brèche du 51",
  "orientation": "SW",
  "denivele": "900",
  "dif_ski": "5.1",
  "expo": "3",
  "difficulte": "PD+",
  "gpx": null,
  "massif": {
    "id": "22",
    "nom": "Bornes - Aravis"
  },
  "depart": {
    "id": "2333",
    "nom": "Dingy-Saint-Clair",
    "altitude": "601",
    "acces": "Annecy &gt; voie des Aravis &gt; Dingy (place de l'église)",
    "latlon": [
      "45.9104",
      "6.22165"
    ]
  },
  "sommets": {
    "1": {
      "id": "2540",
      "nom": "Tête du Parmelan",
      "altitude": "1832",
      "latlon": [
        "45.9429",
        "6.24465"
      ]
    }
  },
  "refuges": [],
  "variantes": [],
  "materiel": "crampons-piolet , rappel 30m",
  "presentation": "Brèche visible de loin dans la falaise du Parmelan , à droite du 51 qui se dessine le soir dans la falaise.",
  "itineraire": "<br style=\"letter-spacing: 0.48px; background-color: rgb(245, 248, 251);\"><span style=\"letter-spacing: 0.48px; background-color: rgb(245, 248, 251);\">Passer le Pertuis, virer à gauche et&nbsp; longer la falaise direction NE.</span><br style=\"letter-spacing: 0.48px; background-color: rgb(245, 248, 251);\"><span style=\"letter-spacing: 0.48px; background-color: rgb(245, 248, 251);\">On passe sous les couloirs Est du Pertuis, monter NW le troisième, on arrive à une barre à contourner par la droite.</span><br style=\"letter-spacing: 0.48px; background-color: rgb(245, 248, 251);\"><span style=\"letter-spacing: 0.48px; background-color: rgb(245, 248, 251);\">On entre dans une combe suspendue qui domine le chemin d'été. Contourner une deuxième barre par la droite et atteindre en pente douce l'antécime sud du Parmelan 1843 en se méfiant des trous dans le lapiaz.</span><br style=\"letter-spacing: 0.48px; background-color: rgb(245, 248, 251);\"><span style=\"letter-spacing: 0.48px; background-color: rgb(245, 248, 251);\">Descente : longer la falaise jusqu'à arriver à l'entrée de la brèche.</span><br style=\"letter-spacing: 0.48px; background-color: rgb(245, 248, 251);\"><span style=\"letter-spacing: 0.48px; background-color: rgb(245, 248, 251);\">Le couloir central nécessite une désescalade puis vire expo ou rappel.</span><br style=\"letter-spacing: 0.48px; background-color: rgb(245, 248, 251);\"><span style=\"letter-spacing: 0.48px; background-color: rgb(245, 248, 251);\">Il y a un couloir rive gauche plus large à skier mais rappel obligatoire.</span><br style=\"letter-spacing: 0.48px; background-color: rgb(245, 248, 251);\"><span style=\"letter-spacing: 0.48px; background-color: rgb(245, 248, 251);\">On sort de la brèche par une rampe W puis pentes herbeuse. La croupe rive droite est moins sujette au boules... Forêt claire pour rejoindre la Blonniére.</span>",
  "remarques": "",
  "biblio": "",
  "auteur": {
    "id": "12636",
    "pseudo": "LULU3CL185"
  },
  "photos": {
    "1": {
      "id": "6940",
      "com": "",
      "url": "/topos/photos/6940.jpg",
      "auteur": {
        "id": "12636",
        "pseudo": "LULU3CL185"
      }
    }
  }
}