{
  "id": "8534",
  "nom": "Dents Blanches Occidentales, Face Sud",
  "orientation": "SE",
  "denivele": "2200",
  "dif_ski": "5.2",
  "expo": "4",
  "difficulte": "D",
  "gpx": null,
  "massif": {
    "id": "24",
    "nom": "Haut Giffre - Aiguilles Rouges"
  },
  "depart": {
    "id": "288",
    "nom": "Les Allamands",
    "altitude": "1096",
    "acces": "De Samoëns prendre la direction du Col de Joux Plane, dès le deuxieme lacet, au lieu dit &quot;Les Moulins&quot; prendre la direction &quot;Les Allamands&quot; et suivre la route jusqu'au parking 1096m.",
    "latlon": [
      "46.1125",
      "6.7503"
    ]
  },
  "sommets": {
    "1": {
      "id": "1524",
      "nom": "Dents Blanches Occidentales",
      "altitude": "2709",
      "latlon": [
        "46.13",
        "6.817"
      ]
    }
  },
  "refuges": [],
  "variantes": [],
  "materiel": "Corde de 60m. ",
  "presentation": "Descente à ski le 28/03/21 plusieurs orientations, sud? ouest et est. ",
  "itineraire": "Itinéraire complet et exposé sur la partie supérieure. Ressaut en glace/rocher de 30 mètres au milieu qui nous a conduit à faire un rappel à la descente. Grand couloir magnifique de 45° de moyenne sur toute la partie inférieure. ",
  "remarques": "",
  "biblio": "",
  "auteur": {
    "id": "27536",
    "pseudo": "lucas74340"
  },
  "photos": {
    "1": {
      "id": "6916",
      "com": "Itinéraire de montée et descente ",
      "url": "/topos/photos/6916.jpg",
      "auteur": {
        "id": "27536",
        "pseudo": "lucas74340"
      }
    }
  }
}