{
  "id": "926",
  "nom": "Crête de la Seyte, Versant NE",
  "orientation": "NE",
  "denivele": "1370",
  "dif_ski": "2.3",
  "expo": "1",
  "difficulte": "R",
  "gpx": null,
  "massif": {
    "id": "7",
    "nom": "Ecrins"
  },
  "depart": {
    "id": "475",
    "nom": "L'Eychaillon",
    "altitude": "1250",
    "acces": "De Gap ou Briancon, rejoindre l'Argentière la Bessée par la N94, puis prendre la route du Fournel que l'on suit jusqu'au parking de l'Eychaillon.",
    "latlon": [
      "44.787",
      "6.5342"
    ]
  },
  "sommets": {
    "1": {
      "id": "737",
      "nom": "Crête de la Seyte",
      "altitude": "2620",
      "latlon": [
        "44.7771",
        "6.4814"
      ]
    }
  },
  "refuges": [],
  "variantes": [
    {
      "id": 1,
      "nom": "Versant Nord",
      "denivele": "",
      "ski": "3.1",
      "orientation": "N",
      "description": "Du sommet, descendre en versant Nord par le Combal des Prés jusqu\\'au vallon du Fournel, l\\'itinéraire est évident et tout droit, dans une grosse trouée entre les arbres : à faire en conditions sûres. Attention, au deuxième ressaut après avoir rejoint la forêt, tirer sur la gauche (barre rocheuse au centre).\\n\\nDeuxième option : descendre par une combe plus à l\\'Est (peu après être sorti de la forêt), et vers 1800m, récupérer une piste pour rejoindre, vers l\\'Est, l\\'itinéraire classique."
    }
  ],
  "materiel": "",
  "presentation": "",
  "itineraire": "Du parking de l'Eychaillon, suivre la route du vallon du Fournel jusqu'au torrent de Crouzet. Prendre ensuite à gauche la piste forestière en direction du Col d'Anon et la quitter rapidement pour en prendre une autre, à droite, vers le Bois du Simon de l'Aigle.<br>\nPoursuivre par une succesion de clairières puis remonter W-SW la large croupe boisée en rive gauche du Vallon de Crouzet.<br>\nOn sort de la forêt vers 2220m, sur un replat. Continuer vers le SW et franchir un ressaut avant d'obliquer vers l'W pour rejoindre la crête qui devient éffilée et inskiable (croix).<br>\n<br>\n",
  "remarques": "",
  "biblio": "",
  "auteur": {
    "id": "583",
    "pseudo": "matB"
  },
  "photos": {
    "1": {
      "id": "96",
      "com": "Vue sur le sommet au sortir de la foret",
      "url": "/topos/photos/96.jpg",
      "auteur": {
        "id": "583",
        "pseudo": "matB"
      }
    },
    "2": {
      "id": "4575",
      "com": "Localisation des dispositifs de protection du Tétras-lyre",
      "url": "/topos/photos/4575.jpg",
      "auteur": {
        "id": "14916",
        "pseudo": "AgnesV"
      }
    },
    "3": {
      "id": "4663",
      "com": "arrivée en haut de la crête (le sommet n'est pas la croix)",
      "url": "/topos/photos/4663.jpg",
      "auteur": {
        "id": "3518",
        "pseudo": "Vivagel"
      }
    },
    "4": {
      "id": "4664",
      "com": "la crête en entier",
      "url": "/topos/photos/4664.jpg",
      "auteur": {
        "id": "3518",
        "pseudo": "Vivagel"
      }
    }
  }
}