{
  "id": "1263",
  "nom": "Tardevant, Face Nord-Est",
  "orientation": "NE",
  "denivele": "1100",
  "dif_ski": "5.4",
  "expo": "4",
  "difficulte": "D-",
  "gpx": null,
  "massif": {
    "id": "22",
    "nom": "Bornes - Aravis"
  },
  "depart": {
    "id": "253",
    "nom": "Les Confins",
    "altitude": "1430",
    "acces": "Annecy -&gt; Thônes -&gt; La Clusaz -&gt; les Confins OU\r\nBonneville -&gt; Saint Jean de Sixt -&gt; La Clusaz -&gt; les Confins\r\n\r\nATTENTION : le stationnement et les départs se font sur le parking de l'Arpettaz,au bout de la route goudronnée ,800m après la chapelle des Confins. Parking au pied des rando, avec toilettes.",
    "latlon": [
      "45.9231",
      "6.4836"
    ]
  },
  "sommets": {
    "1": {
      "id": "25",
      "nom": "Tardevant",
      "altitude": "2501",
      "latlon": [
        "45.9266",
        "6.52609"
      ]
    }
  },
  "refuges": [],
  "variantes": [],
  "materiel": "2 piolets, crampons, casque.",
  "presentation": "",
  "itineraire": "Du parking des Confins gagner la combe de la Grande Forclaz et la remonter pratiquemement jusqu'en haut. Là bifurquer à droite et prendre la pente située au-dessus de la barre rocheuse. La remonter jusqu'au moment où la pente se redresse (50-55°) et emprunter un petit couloir peu marqué qui mène jusqu'en haut.",
  "remarques": "La course est longue parce qu'il faut déjà du temps pour arriver au pied des difficultés.\r\n[b]Fin de descente alternative[/b] : Pierre Tardivel signale un petit couloir permettant de descendre le bas dans la barre.",
  "biblio": "",
  "auteur": {
    "id": "1687",
    "pseudo": "Sylvain--"
  },
  "photos": {
    "1": {
      "id": "352",
      "com": "La face Nord-Est de Tardevant",
      "url": "/topos/photos/352.jpg",
      "auteur": {
        "id": "1687",
        "pseudo": "Sylvain--"
      }
    },
    "2": {
      "id": "355",
      "com": "Le bas de la face nord-est.",
      "url": "/topos/photos/355.jpg",
      "auteur": {
        "id": "1687",
        "pseudo": "Sylvain--"
      }
    },
    "3": {
      "id": "1755",
      "com": "La face vue du Mont Fleuri",
      "url": "/topos/photos/1755.jpg",
      "auteur": {
        "id": "575",
        "pseudo": "Pedro"
      }
    }
  }
}