{
  "id": "665",
  "nom": "Col de la Mariande, Versant Nord",
  "orientation": "NE",
  "denivele": "1700",
  "dif_ski": "2.3",
  "expo": "2",
  "difficulte": "F",
  "gpx": null,
  "massif": {
    "id": "7",
    "nom": "Ecrins"
  },
  "depart": {
    "id": "86",
    "nom": "Saint Christophe en Oisans (le Clot)",
    "altitude": "1383",
    "acces": "Grenoble -&gt; Bourg d'Oisans -&gt; Saint Christophe en Oisans -&gt; La Bernardière -&gt; Le Clot\r\nGrenoble-&gt;Bourg d'Oisans-&gt;St Christophe en Oisans -&gt; Champhorent",
    "latlon": [
      "44.9396",
      "6.19116"
    ]
  },
  "sommets": {
    "1": {
      "id": "509",
      "nom": "Col de la Mariande",
      "altitude": "2940",
      "latlon": [
        "44.8993",
        "6.1534"
      ]
    }
  },
  "refuges": [],
  "variantes": [],
  "materiel": "Piolet, crampons.",
  "presentation": "",
  "itineraire": "Du Clos d'en bas, suivre le vénéon rive droite que l'on franchit au niveau d'une passerelle. Prendre un chemin raide qui conduit aux ruines de la Gassaudière. De là, une petite descente permet d'accéder au torrent de la mariande que l'on franchit. suivre le chemin évident qui permet de franchir le verrou (alt 1950m). Remonter le fond de vallée puis la moraine qui permet d'atteindre un replat à 2470m environ. Obliquer à droite (w) et remonter facilement les pentes avec quelques courts passages à 35° en passant à proximité du lac de la mariande (2604m). On atteint rapidement le col de la mariande à 2940m.\r\nDescente par le même itinéraire.\r\n\r\n- Il est aussi possible d'aller visiter le col de la Haute Pisse ou le Col du Salude.\r\n- Vallon trés sauvage\r\n- Les premiers 300m dans la forêt sont difficilement skiable.\r\n- Du col, possibilité d'atteindre un replat situé plus au nord au pied des rochers de la Pointe de la Mariande. On atteint alors l'altitude de 3020m.\r\n",
  "remarques": "[b]Parc national des Ecrins, chiens interdits[/b]\r\n",
  "biblio": "Toponeige Ecrins Nord",
  "auteur": {
    "id": "103",
    "pseudo": "vertacomi"
  },
  "photos": {
    "1": {
      "id": "2691",
      "com": "Vallon de la Mariande",
      "url": "/topos/photos/2691.jpg",
      "auteur": {
        "id": "761",
        "pseudo": "Cisou"
      }
    }
  }
}